vallaristesttest/__init__.py
vallaristesttest/perform.py
vallaristesttest-0.0.4.dist-info/LICENSE.txt
vallaristesttest-0.0.4.dist-info/METADATA
vallaristesttest-0.0.4.dist-info/WHEEL
vallaristesttest-0.0.4.dist-info/top_level.txt
vallaristesttest-0.0.4.dist-info/RECORD
